PySimpleTest/PySimpleTest.py
PySimpleTest/__init__.py
PySimpleTest/enhance.py
PySimpleTest/helper.py
PySimpleTest/progressbar.py
PySimpleTest/speaker.py
PySimpleTest-1.1.0.dist-info/METADATA
PySimpleTest-1.1.0.dist-info/WHEEL
PySimpleTest-1.1.0.dist-info/top_level.txt
PySimpleTest-1.1.0.dist-info/RECORD
