Metadata-Version: 2.1
Name: PySimpleTest
Version: 1.1.0
Summary: A very simple test framework
Home-page: https://github.com/Time-Coder/PySimpleTest
Author: Time-Coder
Author-email: binghui.wang@foxmail.com
License: UNKNOWN
Platform: UNKNOWN
Classifier: Programming Language :: Python :: 3
Classifier: License :: OSI Approved :: MIT License
Classifier: Operating System :: OS Independent
Requires-Dist: PySimpleGUI
Requires-Dist: colorama
Requires-Dist: pyttsx3
